swagger_server/__init__.py
swagger_server/__main__.py
swagger_server/encoder.py
swagger_server/util.py
swagger_server/controllers/__init__.py
swagger_server/controllers/authorization_controller.py
swagger_server/controllers/command_apis_controller.py
swagger_server/controllers/resource_apis_controller.py
swagger_server/models/__init__.py
swagger_server/models/base_model_.py
swagger_server/models/error.py
swagger_server/models/pet.py
swagger_server/models/pets.py
swagger_server/models/store_info.py
swagger_server/swagger/swagger.yaml
swagger_server/test/__init__.py
swagger_server/test/test_command_apis_controller.py
swagger_server/test/test_resource_apis_controller.py
sourav_pet_project-1.2.0.dist-info/METADATA
sourav_pet_project-1.2.0.dist-info/WHEEL
sourav_pet_project-1.2.0.dist-info/entry_points.txt
sourav_pet_project-1.2.0.dist-info/top_level.txt
sourav_pet_project-1.2.0.dist-info/RECORD
