Metadata-Version: 2.1
Name: sourav-pet-project
Version: 1.2.0
Summary: Sokurav's pet prokjkect
Home-page: UNKNOWN
Author: UNKNOWN
Author-email: UNKNOWN
License: UNKNOWN
Keywords: Swagger,Swagger Petstore
Platform: UNKNOWN
Requires-Dist: connexion
